{
  "RouteAuthorization": {},
  "Hosts": [
    "http://localhost:5400"
  ],
  "Cors": [],
  "DataProtectionKey": "ABA113FC66D1519D3ED16439A563C67F716875E10E45931CA9D7144280E77756",
  "Enabled": false,
  "DebugMode": false,
  "SeedMode": false,
  "RefreshTokenLifetime": 15,
  "ThrottlePolicy": {
    "IpThrottling": true,
    "IpWhitelist": [],
    "IpRules": {},
    "ClientThrottling": true,
    "ClientWhitelist": [],
    "ClientRules": {
      "test": {
        "PerSecond": 1,
        "PerMinute": 10,
        "PerHour": 0,
        "PerDay": 0,
        "PerWeek": 0
      }
    },
    "EndpointThrottling": true,
    "EndpointWhitelist": [],
    "EndpointRules": {
      "/api/oauth/token": {
        "PerSecond": 1,
        "PerMinute": 5,
        "PerHour": 0,
        "PerDay": 0,
        "PerWeek": 0
      }
    },
    "StackBlockedRequests": true,
    "Rates": {
      "Second": 1,
      "Minute": 60
    }
  },
  "FallbackClientKey": "test",
  "RequestLogLevel": 128
}